{
  "survey_slug": "unions",
  "retire_labels": ["Ongoing multi-year survey"],
  "releases": [
    {
      "label": "ShapePipe shear catalogue",
      "release_date": null,
      "release_year": 2022,
      "summary": "First weak-lensing analysis of UNIONS/CFIS r-band data spanning 1,700 deg2: a catalogue with measured shapes for 40 million galaxies (effective density 6.8 per arcmin2), produced with the ShapePipe pipeline (Guinot et al. 2022). Basis for cosmological studies toward the completed 4,800 deg2 UNIONS lensing survey. No public archive download location is stated in the paper; access is via the UNIONS consortium.",
      "n_objects": 40000000,
      "sky_coverage_deg2": 1700,
      "data_volume_tb": null,
      "doi": "10.1051/0004-6361/202141847",
      "bibcode": "2022A&A...666A.162G",
      "url": "https://www.skysurvey.cc/",
      "status": "released"
    },
    {
      "label": "Survey overview (Gwyn et al. 2025)",
      "release_date": null,
      "release_year": 2025,
      "summary": "UNIONS survey overview (AJ 170, 324): ugriz imaging of a core region of 6,250 deg2 of the northern sky with CFHT MegaCam (u, r), Subaru HSC (g, z) and Pan-STARRS (i, z), to 10-sigma point-source depths of u=23.7, g=24.5, r=24.2, i=23.8, z=23.3 (AB, 2 arcsec aperture). Per-band coverage as of January 2025: u 8,327, g 5,755, r 5,638, i 7,717, z_PS 3,988, z_HSC 3,514 deg2 (including extra-footprint area). No formally labelled public data release exists yet — the 'Data Releases 1-4' in the paper are internal Pan-STARRS stack sets; sky coverage is browsable at CADC. Survey ongoing with extensions from 2025.",
      "n_objects": null,
      "sky_coverage_deg2": 6250,
      "data_volume_tb": null,
      "doi": "10.3847/1538-3881/ae03ab",
      "bibcode": "2025AJ....170..324G",
      "url": "https://www.skysurvey.cc/",
      "status": "released"
    }
  ]
}
